MANIFEST.in
README.md
requirements.txt
setup.cfg
setup.py
versioneer.py
nflex_connector_utils/__init__.py
nflex_connector_utils/_version.py
nflex_connector_utils/account.py
nflex_connector_utils/appliance.py
nflex_connector_utils/circuit.py
nflex_connector_utils/colo_space.py
nflex_connector_utils/compute_pool.py
nflex_connector_utils/connections.py
nflex_connector_utils/errors.py
nflex_connector_utils/image_detail.py
nflex_connector_utils/ip_address.py
nflex_connector_utils/locations.py
nflex_connector_utils/logger.py
nflex_connector_utils/metadata.py
nflex_connector_utils/network.py
nflex_connector_utils/parser.py
nflex_connector_utils/resource.py
nflex_connector_utils/rfc3339.py
nflex_connector_utils/saas_user.py
nflex_connector_utils/server.py
nflex_connector_utils/service_offering.py
nflex_connector_utils/tasks.py
nflex_connector_utils/time.py
nflex_connector_utils/tools.py
nflex_connector_utils/volume.py
nflex_connector_utils.egg-info/PKG-INFO
nflex_connector_utils.egg-info/SOURCES.txt
nflex_connector_utils.egg-info/dependency_links.txt
nflex_connector_utils.egg-info/requires.txt
nflex_connector_utils.egg-info/top_level.txt
nflex_connector_utils/tests/__init__.py
nflex_connector_utils/tests/test_account.py
nflex_connector_utils/tests/test_connections.py
nflex_connector_utils/tests/test_errors.py
nflex_connector_utils/tests/test_image_detail.py
nflex_connector_utils/tests/test_ip_address.py
nflex_connector_utils/tests/test_locations.py
nflex_connector_utils/tests/test_metadata.py
nflex_connector_utils/tests/test_parse_mappings.py
nflex_connector_utils/tests/test_parser.py
nflex_connector_utils/tests/test_resources.py
nflex_connector_utils/tests/test_rfc3339.py
nflex_connector_utils/tests/test_saas_users.py
nflex_connector_utils/tests/test_tasks.py
nflex_connector_utils/tests/test_time.py