Metadata-Version: 1.1
Name: nflex-connector-utils
Version: 0.2.0
Summary: nflex-connector-utils provides a suite of tools to produce data structures when implementing resources connector nflex modules.
Home-page: http://www.ntt.com
Author: NTT communications
Author-email: UNKNOWN
License: GNU General Public License v2 (GPLv2)
Platform: UNKNOWN
Classifier: Development Status :: 4 - Beta
Classifier: Environment :: Console
Classifier: Intended Audience :: Developers
Classifier: License :: OSI Approved :: GNU General Public License v2 (GPLv2)
Classifier: Natural Language :: English
Classifier: Programming Language :: Python :: 2.7
Classifier: Programming Language :: Python :: 3.4
Classifier: Programming Language :: Python :: 3.5
Classifier: Programming Language :: Python :: 3.6
Classifier: Topic :: Software Development
